{
    "listings": [
        {
            "address": "45 Av de Lombez, 31300 Toulouse, France",
            "name": "S.C.P Le Bec Mazel-Saltre Lanusse-Crousse Senie Gadek L\u00e9ger"
        },
        {
            "address": "14 Rue Roquelaine, 31000 Toulouse, France",
            "name": "Saint Sulpice SYNLAB Paris"
        },
        {
            "address": "28 Chemin de Cayras, 31400 Toulouse, France",
            "name": "Lieu Pur Vie Saine"
        },
        {
            "address": "13 avenue Edouard Debat Ponsan, 31000 Toulouse, France",
            "name": "ADH-OK"
        },
        {
            "address": "17 avenue de Grande Bretagne, 31300 Toulouse, France",
            "name": "Amplifon Toulouse Patte d'Oie"
        },
        {
            "address": "6 Rue Lakanal, 31000 Toulouse, France",
            "name": "Sup admission"
        },
        {
            "address": "7 Rue du Professeur Gaston Dupouy, 31100 Toulouse, France",
            "name": "Hypnoth\u00e9rapeute-Toulouse"
        },
        {
            "address": "37 Rue Riquet, 31000 Toulouse, France",
            "name": "Ki Shiatsu Toulouse"
        },
        {
            "address": "8 Place du Ravelin, 31300 Toulouse, France",
            "name": "COUOT ARMELLE"
        },
        {
            "address": "32 Chemin de Beauregard, 31300 Toulouse, France",
            "name": "marabout tours professeur Toubaka"
        },
        {
            "address": "14 Boulevard Lazare Carnot, 31000 Toulouse, France",
            "name": "Audioproth\u00e9siste Toulouse Audition Sant\u00e9"
        },
        {
            "address": "4 route de Bayonne, 31300 Toulouse, France",
            "name": "Audioproth\u00e9siste Toulouse Audition Sant\u00e9"
        },
        {
            "address": "Centre Commercial Auchan Gramont, 31075 Toulouse, France",
            "name": "Audioproth\u00e9siste Toulouse-Alain Afflelou Acousticien"
        },
        {
            "address": "31 all\u00e9e Jean Jaur\u00e8s, 31000 Toulouse, France",
            "name": "Amplifon Toulouse"
        },
        {
            "address": "36 54 Route De Bayonne, 31300 Toulouse, France",
            "name": "Audioproth\u00e9siste Krys Audition"
        },
        {
            "address": "1 Rue Croix Baragnon, 31000 Toulouse, France",
            "name": "Audioproth\u00e9siste Krys Audition"
        },
        {
            "address": "46 All\u00e9e Jean Jaur\u00e8s, 31100 Toulouse, France",
            "name": "Audioproth\u00e9siste Toulouse-Alain Afflelou Acousticien"
        },
        {
            "address": "35 route d'Agde, 31500 Toulouse, France",
            "name": "Audioproth\u00e9siste Toulouse La Roseraie Audition Sant\u00e9"
        },
        {
            "address": "102 Rue de la Providence, 31500 Toulouse, France",
            "name": "CR COACHING"
        },
        {
            "address": "12 Rue Arnaud Vidal, 31000 Toulouse, France",
            "name": "Alice Chassaing Mas Sophrologue"
        }
    ]
}